acgen_by_den/__init__.py
acgen_by_den/__main__.py
acgen_by_den/adb_handler.py
acgen_by_den/config_manager.py
acgen_by_den/csv_handler.py
acgen_by_den/feature_handler.py
acgen_by_den/game_data_getter.py
acgen_by_den/helper.py
acgen_by_den/item.py
acgen_by_den/locale_handler.py
acgen_by_den/managed_item.py
acgen_by_den/parse_save.py
acgen_by_den/patcher.py
acgen_by_den/root_handler.py
acgen_by_den/serialise_save.py
acgen_by_den/server_handler.py
acgen_by_den/tracker.py
acgen_by_den/updater.py
acgen_by_den/user_input_handler.py
acgen_by_den/edits/__init__.py
acgen_by_den/edits/basic/__init__.py
acgen_by_den/edits/basic/basic_items.py
acgen_by_den/edits/basic/catfruit.py
acgen_by_den/edits/basic/catseyes.py
acgen_by_den/edits/basic/ototo_base_mats.py
acgen_by_den/edits/basic/talent_orbs.py
acgen_by_den/edits/basic/talent_orbs_new.py
acgen_by_den/edits/cats/__init__.py
acgen_by_den/edits/cats/cat_helper.py
acgen_by_den/edits/cats/cat_id_selector.py
acgen_by_den/edits/cats/chara_drop.py
acgen_by_den/edits/cats/clear_cat_guide.py
acgen_by_den/edits/cats/evolve_cats.py
acgen_by_den/edits/cats/get_remove_cats.py
acgen_by_den/edits/cats/talents.py
acgen_by_den/edits/cats/upgrade_blue.py
acgen_by_den/edits/cats/upgrade_cats.py
acgen_by_den/edits/gamototo/__init__.py
acgen_by_den/edits/gamototo/fix_gamatoto.py
acgen_by_den/edits/gamototo/gamatoto_xp.py
acgen_by_den/edits/gamototo/helpers.py
acgen_by_den/edits/gamototo/ototo_cat_cannon.py
acgen_by_den/edits/levels/__init__.py
acgen_by_den/edits/levels/aku.py
acgen_by_den/edits/levels/allow_filibuster_clearing.py
acgen_by_den/edits/levels/behemoth_culling.py
acgen_by_den/edits/levels/clear_tutorial.py
acgen_by_den/edits/levels/enigma_stages.py
acgen_by_den/edits/levels/event_stages.py
acgen_by_den/edits/levels/gauntlet.py
acgen_by_den/edits/levels/itf_timed_scores.py
acgen_by_den/edits/levels/legend_quest.py
acgen_by_den/edits/levels/main_story.py
acgen_by_den/edits/levels/outbreaks.py
acgen_by_den-0.0.9.dist-info/METADATA
acgen_by_den-0.0.9.dist-info/WHEEL
acgen_by_den-0.0.9.dist-info/top_level.txt
acgen_by_den-0.0.9.dist-info/RECORD
